saltstack_age/__init__.py
saltstack_age/cli.py
saltstack_age/identities.py
saltstack_age/passphrase.py
saltstack_age/secure_value.py
saltstack_age/renderers/__init__.py
saltstack_age/renderers/age.py
saltstack_age-0.4.0.dist-info/METADATA
saltstack_age-0.4.0.dist-info/WHEEL
saltstack_age-0.4.0.dist-info/entry_points.txt
saltstack_age-0.4.0.dist-info/RECORD
