Metadata-Version: 2.3
Name: saltstack-age
Version: 0.4.0
Summary: age renderer for Saltstack
Project-URL: Homepage, https://github.com/pmuller/saltstack-age
Project-URL: Repository, https://github.com/pmuller/saltstack-age.git
Project-URL: Issues, https://github.com/pmuller/saltstack-age/issues
Project-URL: Changelog, https://github.com/pmuller/saltstack-age/blob/main/CHANGELOG.md
Author: Philippe Muller
License: MIT License
Keywords: age,encryption,pillar,salt,saltstack,security
Classifier: Development Status :: 4 - Beta
Classifier: Intended Audience :: System Administrators
Classifier: License :: OSI Approved :: MIT License
Classifier: Programming Language :: Python :: 3
Classifier: Programming Language :: Python :: 3.10
Classifier: Programming Language :: Python :: 3.11
Classifier: Programming Language :: Python :: 3.12
Classifier: Topic :: Security
Classifier: Topic :: System :: Systems Administration
Requires-Python: >=3.8
Requires-Dist: pyrage>=1.1.2
